LICENSE.txt
MANIFEST.in
README.md
setup.cfg
setup.py
pytest_ver/__init__.py
pytest_ver.egg-info/PKG-INFO
pytest_ver.egg-info/SOURCES.txt
pytest_ver.egg-info/dependency_links.txt
pytest_ver.egg-info/requires.txt
pytest_ver.egg-info/top_level.txt
pytest_ver/lib/.gitignore
pytest_ver/lib/__init__.py
pytest_ver/lib/build_info.py
pytest_ver/lib/cfg.py
pytest_ver/lib/cli.py
pytest_ver/lib/constants.py
pytest_ver/lib/harness.py
pytest_ver/lib/protocol.py
pytest_ver/lib/requirements.py
pytest_ver/lib/result_formatter.py
pytest_ver/lib/result_summary.py
pytest_ver/lib/services.py
pytest_ver/lib/status_info.py
pytest_ver/lib/stdout_logger.py
pytest_ver/lib/summary.py
pytest_ver/lib/trace_matrix.py
pytest_ver/lib/utils.py
pytest_ver/lib/verifier.py
pytest_ver/lib/version.json
pytest_ver/lib/iuv/__init__.py
pytest_ver/lib/iuv/iuv.py
pytest_ver/lib/iuv/iuv_data.py
pytest_ver/lib/iuv/iuv_requirements.py
pytest_ver/lib/log/logger.py
pytest_ver/lib/log/logger_stdout.py
pytest_ver/lib/report/__init__.py
pytest_ver/lib/report/report.py
pytest_ver/lib/report/common/__init__.py
pytest_ver/lib/report/common/footer.py
pytest_ver/lib/report/common/gen_base_docx.py
pytest_ver/lib/report/common/gen_base_minhtml.py
pytest_ver/lib/report/common/gen_base_pdf.py
pytest_ver/lib/report/common/gen_base_txt.py
pytest_ver/lib/report/common/header.py
pytest_ver/lib/report/common/page_details.py
pytest_ver/lib/report/common/page_info.py
pytest_ver/lib/report/protocol/__init__.py
pytest_ver/lib/report/protocol/gen_tp_base.py
pytest_ver/lib/report/protocol/gen_tp_docx.py
pytest_ver/lib/report/protocol/gen_tp_minhtml.py
pytest_ver/lib/report/protocol/gen_tp_pdf.py
pytest_ver/lib/report/protocol/gen_tp_txt.py
pytest_ver/lib/report/summary/__init__.py
pytest_ver/lib/report/summary/gen_summary_base.py
pytest_ver/lib/report/summary/gen_summary_docx.py
pytest_ver/lib/report/summary/gen_summary_minhtml.py
pytest_ver/lib/report/summary/gen_summary_pdf.py
pytest_ver/lib/report/summary/gen_summary_txt.py
pytest_ver/lib/report/trace_matrix/__init__.py
pytest_ver/lib/report/trace_matrix/gen_trace_matrix_base.py
pytest_ver/lib/report/trace_matrix/gen_trace_matrix_docx.py
